sideload_nu_0_bin_6633d874acd3cb34a842029f/__init__.py
sideload_nu_0_bin_6633d874acd3cb34a842029f-1.0.0.dist-info/METADATA
sideload_nu_0_bin_6633d874acd3cb34a842029f-1.0.0.dist-info/WHEEL
sideload_nu_0_bin_6633d874acd3cb34a842029f-1.0.0.dist-info/top_level.txt
sideload_nu_0_bin_6633d874acd3cb34a842029f-1.0.0.dist-info/RECORD
